LICENSE
MANIFEST.in
Makefile
README.md
TODO
setup.cfg
setup.py
examples/hexdump
examples/prettyprint
examples/simpletest
fudgemsg/__init__.py
fudgemsg/codecs.py
fudgemsg/field.py
fudgemsg/message.py
fudgemsg/prefix.py
fudgemsg/registry.py
fudgemsg/types.py
fudgemsg.egg-info/PKG-INFO
fudgemsg.egg-info/SOURCES.txt
fudgemsg.egg-info/dependency_links.txt
fudgemsg.egg-info/top_level.txt
fudgemsg/taxonomy/__init__.py
fudgemsg/taxonomy/map.py
fudgemsg/taxonomy/mapresolver.py
fudgemsg/utils/__init__.py
fudgemsg/utils/hexdump.py
fudgemsg/utils/render.py
tests/__init__.py
tests/test_codecs.py
tests/test_field.py
tests/test_field_decode.py
tests/test_maptaxonomy.py
tests/test_maptaxonomyresolver.py
tests/test_message.py
tests/test_prefix.py
tests/test_registry.py
tests/test_types.py
tests/data/allNames.dat
tests/data/allOrdinals.dat
tests/data/dateTimes.dat
tests/data/deeper_fudge_msg.dat
tests/data/fixedWidthByteArrays.dat
tests/data/subMsg.dat
tests/data/unknown.dat
tests/data/variableWidthColumnSizes.dat
tests/func_tests/__init__.py
tests/func_tests/test_deeper_msg.py
tests/func_tests/test_simpletest.py
tests/func_tests/test_submsg.py