Metadata-Version: 1.0
Name: fudgemsg
Version: 0.1
Summary: Fudge is a hierarchical, typesafe, binary, self-describing message encoding system.
Home-page: http://github.com/joequant/Fudge-Python
Author: Joseph C Wang
Author-email: joequant@gmail.com
License: APL2
Platform: UNKNOWN
